{
  "member_name": "木戸口 英司",
  "kana": "きどぐち えいじ",
  "generated_at": "2025-11-09T12:19:41.526769+00:00",
  "keywords": [
    "障害福祉",
    "障害 福祉",
    "障がい 福祉",
    "障害者 福祉",
    "障がい者 福祉",
    "障害者",
    "障がい者",
    "障害児 福祉",
    "障がい児 福祉",
    "障害児",
    "障がい児",
    "医療的ケア児",
    "放課後等デイサービス",
    "特別児童扶養手当",
    "障害児福祉手当",
    "特別障害者手当"
  ],
  "meetings": [
    {
      "issueID": "120814601X00620220329",
      "date": "2022-03-29",
      "nameOfMeeting": "総務委員会",
      "issue": "第6号",
      "session": 208,
      "speeches": [
        {
          "speechID": "120814601X00620220329_229",
          "speechOrder": 229,
          "speaker": "木戸口英司",
          "speech": "○木戸口英司君　私は、ただいま承認されました放送法第七十条第二項の規定に基づき、承認を求めるの件に対し、自由民主党・国民の声、立憲民主・社民、公明党及び国民民主党・新緑風会の各派共同提案による附帯決議案を提出いたします。\r\n　案文を朗読いたします。\r\n　　　　放送法第七十条第二項の規定に基づき、承認を求めるの件に対する附帯決議（案）\r\n　　政府及び日本放送協会は、公共放送の使命を全うし、国民・視聴者の信頼に応えることができるよう、次の事項についてその実現に努めるべきである。\r\n　一、協会は、公共放送としての社会的使命を認識し、公正を保持し、事実を客観的かつ正確、公平に伝え、真実に迫るための最善の努力を不断に行うとともに、意見が分かれている問題については、できる限り多くの角度から論点を明らかにするなど、放送法の原則を遵守すること。また、国民・視聴者から寄せられる様々な意見に対し、必要に応じ自律的に調査し、その結果を速やかに公表すること。\r\n　二、政府は、日本国憲法で保障された表現の自由、放送法に定める放送の自律性を尊重し、協会を含めた放送事業者の番組編集における自主・自律性が保障されるように放送法を運用すること。\r\n　　　また、経営委員の任命に当たっては、その職務の公共性を認識し、公正な判断をすることができる経験と見識を有する者を、教育、文化等の各分野及び全国各地方から公平に代表されることを考慮するとともに、女性委員の比率を引き上げることなどにより多様な意見が反映されるよう、幅広く選任するべく努めること。\r\n　三、経営委員会は、放送法が定める協会の自律性を保障するために、協会の経営に関する最高意思決定機関として重い職責を担っていることを深く認識し、協会が放送法に定められた役割を確実に果たすよう、権限を行使すること。その際、放送番組は何人からも干渉され、又は規律されることがないことを規定した、放送法第三条の放送番組編集の自由を十分理解し、その自由を侵害する行為はもとより、侵害を疑われる行為を絶対に行わないこと。\r\n　　　また、協会は、国民・視聴者からの受信料でその運営が行われていることを深く認識し、その運営について、放送法を遵守し、情報の十分な開示・説明を行うこと。特に、経営委員会及び理事会等における業務・経営等についての意思決定過程を明らかにするため、経営委員会及び理事会の議事録の適切な作成・管理を行うとともに、原則としてこれを公表すること。\r\n　四、協会は、関連団体を含めた不祥事に対し、国民・視聴者から厳しい批判が寄せられていることを踏まえ、公共放送を担う者としての役職員の倫理観を高め、綱紀の粛正、コンプライアンスの徹底、再発防止策の確実な実施等を組織一体となって行うことにより、信頼回復に全力を尽くすこと。\r\n　五、政府及び協会は、放送と通信の融合の更なる進展の中で、公共放送の在り方及び受信料の在り方について、引き続き真摯に検討を行うこと。\r\n　　　また、その結果を踏まえ、政府は、所要の措置を講ずるとともに、協会は、新しい社会と技術に対応した公共メディアとしての経営ビジョンを構築すること。\r\n　六、協会は、繰越金や今後の事業収支見通しと新型コロナウイルス感染症の拡大の影響等を踏まえ、国民・視聴者の負担軽減に資するよう、中期経営計画で示した受信料の引下げの内容を早期に具体化するとともに、受信料の支払いが困難となった者について、支払いの猶予等の対応を適切に行うほか、受信料減免の拡大について引き続き検討すること。\r\n　　　また、受信料制度に対する国民・視聴者の理解を促進し、受信契約の締結は視聴者の理解を得た適正なものでなければならないことを認識した上で、訪問によらない営業への移行による関係者に対する影響等に十分留意しつつ、公平負担の観点から、受信料支払率の向上に努めること。\r\n　七、協会は、放送センターの建替えに際し、受信料を財源としていることを踏まえ、中期経営計画で示された「新放送センターの建設計画の抜本的な見直し」の具体的な内容を早期に明らかにし、国民・視聴者の理解が得られるよう説明を尽くすとともに、建替えに係る費用の圧縮に徹底的に取り組み、その成果を国民・視聴者に適切に還元すること。\r\n　八、協会は、グループとしてのガバナンスを不断に強化し、子会社等からの適切な還元を図るとともに、重複業務の整理等を推進し、透明性の高い効率的なグループ経営の構築に向けて、迅速かつ確実に取り組むこと。\r\n　九、協会は、常時同時配信等のインターネット活用業務を行うに際しては、その影響力の大きさを十分認識し、国民・視聴者のニーズや動向を的確に把握するとともに、社会実証の結果や民間放送事業者等の見解に十分留意しつつ、関係者間での情報共有及び連携を図り、適正な規模・水準の下、節度をもって適切に実施すること。\r\n　十、協会は、各地域の関係者と様々な分野で連携を強化しながら、それぞれの地域ならではの魅力を紹介し、地域の活性化及び発展に寄与するコンテンツを充実するとともに、国内外に向けた積極的な発信に努めること。\r\n　十一、協会は、激動する国際情勢や新型コロナウイルス感染症の現状に鑑み、我が国の経済・社会・文化等の動向を正しく伝えることの重要性を踏まえ、我が国に対する理解が促進されるとともに、在外邦人に的確な情報が提供されるよう、国際放送及び海外発信の一層の充実を図ること。特に、外国人向けテレビ国際放送については、番組内容の充実、国内外における認知度の向上等に努めること。\r\n　十二、協会は、相次ぐ自然災害や新型コロナウイルス感染症の現状に鑑み、いかなる事態においても放送・サービスが継続されるよう、地方局と連携し、放送設備と体制の強化を図るとともに、正しい情報を国民・視聴者に伝達し、その予防・拡大防止に寄与するよう万全を期すこと。\r\n　十三、協会は、障がい者、高齢者に対し、十分な情報アクセス機会を確保し、デジタル・ディバイドを解消するため、新たな技術の開発・活用などにも取り組み、字幕放送、解説放送、手話放送など「人にやさしい放送」の一層の充実等を図ること。\r\n　十四、協会は、ハラスメント防止の取組を一層促進するとともに、過去に記者が過労で亡くなった事実等を踏まえ、過労死の再発防止のため、協会の業務に携わる者の命と健康を最優先に確保し、適正な業務運営と労働環境改善に全力で取り組むこと。\r\n　　　また、障がい者の雇用率の一層の向上及び女性の採用・登用の拡大を図ること。\r\n　　　右決議する。\r\n　以上でございます。\r\n　何とぞ委員各位の御賛同をお願い申し上げます。",
          "speechURL": "https://kokkai.ndl.go.jp/txt/120814601X00620220329/229"
        }
      ]
    },
    {
      "issueID": "120414889X02220210527",
      "date": "2021-05-27",
      "nameOfMeeting": "内閣委員会",
      "issue": "第22号",
      "session": 204,
      "speeches": [
        {
          "speechID": "120414889X02220210527_168",
          "speechOrder": 168,
          "speaker": "木戸口英司",
          "speech": "○木戸口英司君　私は、ただいま可決されました障害を理由とする差別の解消の推進に関する法律の一部を改正する法律案に対し、自由民主党・国民の声、立憲民主・社民、公明党、日本維新の会、国民民主党・新緑風会及び日本共産党の各派共同提案による附帯決議案を提出いたします。\r\n　案文を朗読いたします。\r\n　　　　障害を理由とする差別の解消の推進に関する法律の一部を改正する法律案に対する附帯決議（案）\r\n　　政府は、本法の施行に当たり、次の諸点について適切な措置を講ずるべきである。\r\n　一　本法の施行は、公布の日から三年を待たず、可能な限り早期に行うこと。\r\n　二　障害を理由とする差別の解消の推進に関する法律についての理解がより一層深まるよう啓発に努めるとともに、本法並びに本法に基づく基本方針、対応要領及び対応指針の改定については、国の各行政機関、地方公共団体及び民間事業者に周知徹底すること。\r\n　三　複合的な差別を含め、障害を理由とする差別の解消を総合的に推進するため、次期障害者基本計画の策定を通じて把握した課題について、障害者基本法及び障害者虐待防止法の見直しを含めて必要な対応を検討すること。\r\n　四　基本方針において、障害者の権利に関する条約の精神にのっとり、差別の定義に係る基本的な考え方を明記することを検討すること。\r\n　五　障害のある女性や性的少数者等への複合的な差別の解消について、基本方針、対応要領及び対応指針に明記することを検討すること。また、地方公共団体と連携して、複合的な差別に関する情報の収集、分析を行うこと。\r\n　六　基本方針等において、障害の分野に応じて、具体的な差別事例や合理的配慮の提供事例を盛り込むことを検討すること。\r\n　七　基本方針、対応要領及び対応方針の改定に当たっては、障害者の権利に関する条約における障害当事者参画の理念等を踏まえ、障害者、障害者団体その他の関係者の意見を聴取すること。\r\n　八　障害者基本計画の実施状況の監視に当たっては、知的障害者及び精神障害者を含む障害者並びに障害者団体の構成員の参画を検討すること。\r\n　九　障害を理由とする差別に関する相談及び紛争の防止又は解決に必要な体制を整備するに当たっては、以下の諸点に留意すること。\r\n　　１　障害を理由とする差別に関する相談について、たらい回しを防止する等の観点から、ワンストップの相談窓口を設けるとともに、国と地方公共団体との連携を強化すること。\r\n　　２　障害者が安心して相談することができるよう、相談窓口における相談対応者に障害者を加えること。\r\n　　３　既存の機関によるこれまでの対応について調査、分析し、その結果を公表すること。\r\n　十　相談窓口については、電話対応だけでなく、ＦＡＸ、電子メール、ＳＮＳ等の利用を可能とするなど、聴覚障害者が利用しやすい体制を整備すること。\r\n　十一　障害を理由とする差別の解消に向けた啓発活動に当たっては、障害者団体等が実施している研修に関する情報を可能な限り収集し、その内容も十分に踏まえて検討すること。\r\n　十二　障害を理由とする差別及びその解消のための取組に関する情報の収集及び整理に当たっては、民間事業者に対し情報の提供等を求めつつ、国の各行政機関及び地方公共団体が協力・連携し、データベースの構築等により、情報を共有すること。\r\n　十三　障害者差別解消法第五条に基づく環境の整備を行うため、公共施設、公共交通機関その他不特定多数の者が利用する施設等のバリアフリー化を推進するための財政措置を含め、必要な措置を講ずること。\r\n　十四　合理的配慮の提供に当たっての意思の表明について、知的障害等により本人の意思の表明が困難な場合には家族、介助者等が本人を補佐して行うことも可能であることを、国の各行政機関、地方公共団体及び民間事業者に十分に周知すること。\r\n　十五　基本方針、対応要領及び対応方針の改定に当たっては、障害の特性に応じて、ルビ、点字、音声等を用いるなど、全ての人に分かりやすい情報提供となるよう配慮すること。\r\n　十六　国の各行政機関又は地方公共団体が合理的配慮を提供しない場合は、その理由を障害者側に十分説明することに努め、その旨を国の各行政機関及び地方公共団体に周知徹底すること。\r\n　十七　障害者差別解消支援地域協議会について、未設置市町村も少なくないことを踏まえ、地方公共団体に対して十分な支援を行うこと。\r\n　十八　法令等において用いられている「障害者」のうかんむりの「害」の字を他の漢字とし、又はひらがなの「がい」とするかどうかの検討に資するため、障害当事者の意向や世論の動向を把握すること。\r\n　　　右決議する。\r\n　以上でございます。\r\n　何とぞ委員各位の御賛同をお願い申し上げます。",
          "speechURL": "https://kokkai.ndl.go.jp/txt/120414889X02220210527/168"
        }
      ]
    },
    {
      "issueID": "120414889X00220210203",
      "date": "2021-02-03",
      "nameOfMeeting": "内閣委員会",
      "issue": "第2号",
      "session": 204,
      "speeches": [
        {
          "speechID": "120414889X00220210203_136",
          "speechOrder": 136,
          "speaker": "木戸口英司",
          "speech": "○木戸口英司君　立憲民主・社民の木戸口英司です。\r\n　私は、ただいま可決されました新型インフルエンザ等対策特別措置法等の一部を改正する法律案に対し、自由民主党・国民の声、立憲民主・社民、公明党及び国民民主党・新緑風会の各派共同提案による附帯決議案を提出いたします。\r\n　案文を朗読いたします。\r\n　　　　新型インフルエンザ等対策特別措置法等の一部を改正する法律案に対する附帯決議（案）\r\n　　政府は、本法の施行に当たり、次の諸点について適切な措置を講ずるべきである。\r\n　一　まん延防止等重点措置を公示する際に満たすべき要件について、新型コロナウイルス感染症対策分科会が提言したステージⅠからⅣ、六つの指標及び目安との関係などを含め、あらかじめ客観的な基準を示すこと。\r\n　二　まん延防止等重点措置の公示については、あらかじめ学識経験者の意見を聴いた上で行うこととし、国会へその旨及び必要な事項について速やかに報告すること。また、まん延防止等重点措置の公示期間の延長、区域変更、又は解除についても同様とすること。\r\n　三　まん延防止等重点措置の公示又は緊急事態宣言（以下「緊急事態宣言等」という。）について、都道府県知事からの要請を受けた場合は、当該要請を最大限尊重し、速やかに検討するとともに、要請に応じない場合は、当該要請を行った都道府県知事に対し、その旨及びその理由を示すこと。また、緊急事態宣言等の延長、区域変更、又は解除についても同様とすること。\r\n　四　まん延防止等重点措置の実施に当たっては、緊急事態措置以上に、国民の自由と権利の制限は必要最小限のものとすること。また、「まん延を防止するために必要な措置」とは、主として営業時間の変更及びみだりに出入りしないことの要請であり、営業時間の変更を超えた休業要請、イベントなどによる施設の使用停止、新型インフルエンザ等対策特別措置法（以下「特措法」という。）第四十五条第一項と同様の全面的な外出自粛要請等は含めないこと。\r\n　五　まん延防止等重点措置においては、国民の自由と権利の制限は必要最小限とすることについて、緊急事態措置における場合より一層配慮すること。また、適用できない「正当な理由」が認められる場合を、具体的なケースを含めガイドラインで明確に示すこと。\r\n　六　緊急事態措置における命令及び過料を適用できない「正当な理由」が認められる場合を、具体的なケースを含めガイドラインで明確に示すこと。\r\n　七　まん延防止等重点措置又は緊急事態措置（以下「緊急事態措置等」という。）に係る要請・命令の公表は、感染拡大防止の観点から逆効果になったり、誹謗中傷行為等が起きたりしないよう、その影響に配慮すること。\r\n　八　緊急事態措置等に係る立入検査の実施に当たっては、原則として立入先の同意を得て行うこととし、同意が得られない場合も物理力の行使等は行わないこと。\r\n　九　罰則・過料の適用に当たっては、国民の自由と権利が不当に侵害されることのないよう、慎重に運用すること。さらに、不服申立てその他救済の権利を保障すること。\r\n　十　入院拒否等に対する過料の適用については、本法に基づく入院勧告から措置に至る全ての手続を丁寧かつ十分に行うとともに、入院困難の理由に対する相談・支援を十分に尽くした上で、慎重に対応すること。また、その際には、現場で円滑に運用がなされるよう、その手順などを分かりやすく示すとともに、適用についての具体例など、適用の適否の判断材料をできる限り明確に示すこと。また、宿泊施設や居宅の場合も含め、本人、その子供や高齢者などの生活維持に配慮するとともに、必要な対応を行うこと。\r\n　十一　積極的疫学調査の拒否等に対する過料の適用については、ＰＣＲ等の検査拒否や陽性結果の秘匿につながるおそれや保健所の対応能力・事務負担等も踏まえ、慎重に行うこととし、現場で円滑に運用がなされるよう、その手順などを分かりやすく示すとともに、適用についての具体例など、適用の適否の判断材料をできる限り明確に示すこと。\r\n　十二　国及び地方自治体は、かつてハンセン病や後天性免疫不全症候群等の患者等に対するいわれなき差別や偏見が存在したことを重く受け止め、国民は何人に対しても不当な差別的取扱い等を行ってはならないことを明確にし、悪質な差別的取扱い等を行った者には法的責任が問われ得ること等も含めて周知を徹底するとともに、不当な差別的取扱い等を受けた者に対する相談支援体制の整備など、万全の措置を講ずること。\r\n　十三　特措法第六十三条の二に基づく「必要な財政上の措置その他の必要な措置」は、同法第二十四条第九項、まん延防止等重点措置及び緊急事態措置に係る要請に応じた事業者に対しては確実に行うものとすること。また、これらの要請に伴う支援については、要請に応じたことのみならず、要請による経営への影響の度合い等を勘案し、公平性の観点や円滑な執行等が行われることにも配慮しつつ、要請に十分な理解と協力を得られるようにするため、必要な支援となるよう努めること。\r\n　十四　新型コロナウイルス感染症の感染拡大により所得が減少している国民並びに協力事業者以外も含めた事業者及びその雇用する労働者に対し、生活及び事業継続等が可能となるよう万全の財政・金融政策を講ずること。\r\n　十五　新型コロナウイルス感染症の感染拡大に伴う自殺が増加していることから、地方自治体と連携し、自殺の原因となり得る事由に対応した効果的な対策を講ずること。\r\n　十六　国及び都道府県は、感染者のための病床等を確保するため、地方自治体及び医療機関等との連携や協力に応じる医療機関への費用、収入等経営状況を踏まえた財政的な支援など必要な措置を講ずること。また、都道府県知事が感染症の予防及び感染症の患者に対する医療に関する法律並びに特措法第二十四条及び第三十一条に基づき必要な要請等を行えるものと解釈すること。さらに、正当な理由がなく勧告に従わない場合の医療関係者等の公表は、医療機関等の事情も考慮し、慎重に行うこと。また、病床等の確保のために既に入院・通院状態にある患者が転院や主治医の交代等を余儀なくされる場合には、精神面でのケアを含め、患者の負担に十分に配慮すること。\r\n　十七　国、都道府県、保健所設置市等の間の情報連携の強化に当たっては、患者等のプライバシーが侵害されることのないよう、個人情報の利用及び関係者による閲覧を必要最小限とすること。また、新型コロナウイルス感染者等情報把握・管理支援システム（ＨＥＲ―ＳＹＳ）の入力作業の効率化に向けたシステム更改等、負担軽減のための措置を講ずること。\r\n　十八　医療機関、介護施設、障害者支援施設等の職員等に対する検査を徹底するとともに、エッセンシャルワーカーや通勤などで感染不安を持つ国民を含め社会経済活動のための検査が希望に応じて速やかに受けられるよう、検査体制の強化に努めるとともに環境整備を進めること。\r\n　十九　濃厚接触者の調査を効果的に実施し、必要な検査を幅広く実施するとともに、濃厚接触者の自宅待機などに対するフォロー体制に万全を期すこと。\r\n　二十　約二週間ごとに変異する新型コロナウイルスに対して、現在流行している変異株を把握し対処するため、ゲノム分子疫学調査（全ゲノムシークエンス）の実施頻度を高め、速やかに公表すること。また、我が国における対策に大きな影響を及ぼし得る新型コロナウイルスの変異株の更なる市中感染拡大を防止するため、遺伝子解析等を実施する検体数の増加、変異株を特定できる技術の確立と普及の促進等、変異株の感染拡大防止に万全を期すこと。さらに、検疫官増員、検査機器充実等の体制強化、感染防止対策が施された移動手段の拡充の支援等水際対策を徹底すること。\r\n　二十一　感染症研究に係る国の機関の人員及び予算の十分な確保を含め、その体制を強化すること。また、地方衛生研究所については、新型コロナウイルス感染症対策における位置付けを明確化し、国立感染症研究所及び保健所との連携を強化すること。\r\n　二十二　新型コロナウイルスに係るワクチン接種を希望する国民に迅速かつ安全・円滑に実施できるよう、副反応情報や、審議会の議事録等の速やかな公表など安全性及び有効性その他の接種の判断に必要な情報を徹底して公表するとともに、住民票の住所地以外に住む者（例えば、単身赴任者や学生、ホームレス等）が現在地でもワクチン接種ができるようにすること。また、地方自治体の接種体制整備に対し人材や財政措置を含む国による最大限の支援を行うとともに、国内に居住する外国人に対しても接種機会を確保し、必要な支援を行うこと。なお、審議会の議事録については、可能な限り早急に公表するとともに、当該ワクチンの接種が開始される前に必ず情報を開示し、その情報に基づく接種判断が行われるよう確保すること。\r\n　二十三　まん延防止等重点措置が設けられること等により、地方自治体においても行動計画の見直し等の対応が必要となることから、特措法の運用指針等を速やかに定め、公表するとともに、運用・解釈に関する地方自治体からの質問に対して迅速かつ誠実に回答すること。\r\n　二十四　現下の新型コロナウイルス感染症の感染拡大までに生じた検査、保健所、医療の諸課題を分析し、今後の感染拡大を最大限に封じ込めるとともに再度の感染拡大が生じた場合に対応可能な検査、保健所、医療提供体制を計画的に確保するため、国としての基本的な方針を示すとともに都道府県等の計画的取組の実施状況を的確に把握し、地域における対策の実効性を確保するために徹底したＰＤＣＡサイクルに基づき必要な措置を講ずること。また、これらの国及び都道府県等の対策の実施状況について適時に公表すること。\r\n　二十五　新型インフルエンザ等の感染拡大に伴う諸課題の共有・解決に向け、与野党に対して必要な情報提供を適時、適切に行うとともに、与野党の意見を尊重して感染症対策の実施に当たること。\r\n　二十六　新型インフルエンザ等の感染拡大により緊急事態宣言等の決定に至り得る場合においては、会議録等の経過記録及び科学的根拠となるデータの保存に万全を期し、国民への説明責任を果たすとともに、海外の関係機関との情報共有を行い、今後の感染症対策のために活用できるようにすること。\r\n　二十七　令和二年五月の緊急事態解除宣言の時期の妥当性など、新型コロナウイルス感染症の感染拡大に関する政府のこれまでの対応について、今後の政府の対応に活用するために、第三者的立場から、客観的、科学的に検証し、その結果を公表すること。\r\n　二十八　今次法改正の実施状況を検証するとともに、前項の検証結果も合わせ、法制度面も含め必要な見直しを行うこと。\r\n　　　右決議する。\r\n　以上でございます。\r\n　何とぞ委員各位の御賛同をお願い申し上げます。",
          "speechURL": "https://kokkai.ndl.go.jp/txt/120414889X00220210203/136"
        }
      ]
    },
    {
      "issueID": "119814889X02220190606",
      "date": "2019-06-06",
      "nameOfMeeting": "内閣委員会",
      "issue": "第22号",
      "session": 198,
      "speeches": [
        {
          "speechID": "119814889X02220190606_037",
          "speechOrder": 37,
          "speaker": "木戸口英司",
          "speech": "○木戸口英司君　国民民主党・新緑風会、木戸口英司です。\r\n　成年被後見人等についての欠格条項は、成年後見制度の創設時に既に国会で指摘されながらも、長らく放置されてきた問題です。本法案が提出されてから審議入りに一年以上を要したことを含め、国の不作為と言わざるを得ません。また、その間、霞が関等における各省庁、これ国会でもありましたけれども、国家公務員の障害者雇用の水増し問題も発覚しております。\r\n　成年被後見人等欠格条項見直し法の早期制定を求める要望書が、全国手をつなぐ育成連合会、日本発達障害ネットワーク、全国肢体不自由児者父母の会連合会、日本肢体不自由児協会、日本ダウン症協会、日本自閉症協会、ＤＰＩ、障害者インターナショナル日本会議から出されております。強い要望、切実な願いだと思います。また、成年被後見人であることで雇い止めをされたのは違憲だとして訴訟を起こした方もいらっしゃいます。障害のある方の社会参画の促進に向けて国全体で改めて取り組んでいかなければならないことを強く申し上げ、質問に入りたいと思います。\r\n　成年後見制度を創設した平成十一年の民法の改正時、当時百五十八あった欠格条項については、主に法務省が中心となって削除したことにより減少したものの、百十六もの規定が残されました。参議院法務委員会は、当時の委員会附帯決議で、「成年被後見人又は被保佐人であることを欠格事由とする百十六件の資格制限規定については、更なる見直しを行うこと。」と指摘しており、政府においても更なる見直しの必要性について認識があったものと考えます。しかしながら、その後、各省における欠格事項の削減見直しは進まず、逆に二百程度まで増加したということになっております。\r\n　結局、今回の全般的な見直しのための法改正に至るまでに約二十年が経過したということでありますけれども、ここに至る経緯、理由について、まず大臣の御説明をお願いいたします。",
          "speechURL": "https://kokkai.ndl.go.jp/txt/119814889X02220190606/37"
        },
        {
          "speechID": "119814889X02220190606_043",
          "speechOrder": 43,
          "speaker": "木戸口英司",
          "speech": "○木戸口英司君　それでは、基本的なところを厚生労働省にお聞きしますけれども、この法令上の欠格条項の見直しということ、今ずっと指摘してきましたけれども、実際に成年後見制度を利用する方が社会参画するための環境整備を進める必要ということは、今大臣からもお話ありました。\r\n　例えば、制度を利用している方が勤務している職場において御本人が抱えている障害、疾病への理解が進めば、その方も円滑に業務をこなすことができるということは当然であります。こういった職場の理解の増進、障害者が働くに当たっての環境整備について、今までそれぞれ取組はあるんだろうと思いますけれども、今回の見直し法も踏まえながら、厚生労働省の取組状況等をお伺いいたしたいと思います。",
          "speechURL": "https://kokkai.ndl.go.jp/txt/119814889X02220190606/43"
        },
        {
          "speechID": "119814889X02220190606_047",
          "speechOrder": 47,
          "speaker": "木戸口英司",
          "speech": "○木戸口英司君　やはり、財産管理を超えて、この身上監護に期待が大きいということはそのとおりだと思います。\r\n　また、利用者本人や親族と面識がない専門職後見人が選任され、御本人や親族と後見人との間でトラブルとなるなどの事案も間々あるということ、御本人の事情をよく理解している親族が選任されることで御本人もより安心して制度を利用できるということ、それはもうそのとおりだと思います。\r\n　一方、今指摘があったとおり、核家族化が進んでいることから、将来的には親族がいない、縁がないという高齢者、障害者も多数出てくるということ、そういう中でこの専門職、市民の後見人の需要がますます増えてくるということもこれ言えるんではないかと思いますけれども、この点について政府の認識をお伺いいたします。",
          "speechURL": "https://kokkai.ndl.go.jp/txt/119814889X02220190606/47"
        }
      ]
    },
    {
      "issueID": "119814889X01120190423",
      "date": "2019-04-23",
      "nameOfMeeting": "内閣委員会",
      "issue": "第11号",
      "session": 198,
      "speeches": [
        {
          "speechID": "119814889X01120190423_050",
          "speechOrder": 50,
          "speaker": "木戸口英司",
          "speech": "○木戸口英司君　財源の問題もあるということを言われました。やはり大事な、やはり要望の多いところだと思いますので、大臣もそこは御認識されていてということだろうと想像をいたしますけれども、この点は今後また早めに、早期に検討され、充実されていくことを私も希望したいと思います。\r\n　これ、地方自治体における障害児保育の整備の必要性ということでありますけれども、財政難などを理由に自治体で公立認可保育園を民営化する動きが加速しております。元々は公立園の数の方が多かったとのことですけれども、厚生労働省の調査によると、平成二十九年十月一日現在では、総数二万七千百三十七園のうち、公立園は八千七百十六園と全体の三割にすぎなくなっております。多くの公立園が障害児を受け入れてきた実績から、公立園は障害児保育のノウハウが蓄積されている、行き場を失う子が出かねないといった声が保護者から上がっています。\r\n　民間園の中には人手不足や経験がないなどの理由で障害児を受け入れていないところもあるとのことですが、政府はこの実態を把握しておられますでしょうか。保育施設に入れなければ無償化の対象にもなり得ませんし、その保護者の経済的負担の軽減も図られません。必要に応じて障害児が十分に保育を受けられるよう政府として何らかの施策を講じる必要があると考えますが、見解をお伺いいたします。",
          "speechURL": "https://kokkai.ndl.go.jp/txt/119814889X01120190423/50"
        }
      ]
    },
    {
      "issueID": "119714889X00420181122",
      "date": "2018-11-22",
      "nameOfMeeting": "内閣委員会",
      "issue": "第4号",
      "session": 197,
      "speeches": [
        {
          "speechID": "119714889X00420181122_134",
          "speechOrder": 134,
          "speaker": "木戸口英司",
          "speech": "○木戸口英司君　希望の会（自由・社民）、木戸口英司です。\r\n　人事院勧告、給与法の改定ということで、今、清水委員からもお話ありました国家公務員の総人件費に関する基本方針が出ております。その関係の中で、簡素で効率的な行政組織体制を確立すると、先ほど来大臣からもお話があったとおりです。それと併せて、先ほど来質疑で働き方改革の話も随分出てまいりました。\r\n　そこで、ちょっと併せて、質問をちょっと変えて大臣に所見をお伺いしたいんですが、公務部門における障害者の不適切計上が、これもずっと議論があったところです。こういった簡素、効率的な行政組織ということを進める中で、働き方改革もあり、国の行政機関等の過大な業務負担、これが現場の余裕のなさを生んで、障害者雇用への消極性、そういったことを招いてこのような深刻な水増しを招いている側面があるのではないかということを、ずっと質疑を聞きながら私はそのような考えを持ったのでありますけれども、この点について、大臣、所見があればお伺いしたいと思います。",
          "speechURL": "https://kokkai.ndl.go.jp/txt/119714889X00420181122/134"
        }
      ]
    },
    {
      "issueID": "119615104X00920180517",
      "date": "2018-05-17",
      "nameOfMeeting": "文教科学委員会",
      "issue": "第9号",
      "session": 196,
      "speeches": [
        {
          "speechID": "119615104X00920180517_116",
          "speechOrder": 116,
          "speaker": "木戸口英司",
          "speech": "○木戸口英司君　今日はここまでにしておきますけれども、文科省が国家戦略特区のワーキンググループに呼ばれて、その最後が二〇一六年の九月十六日ですけれども、この時点でも慎重な意見を述べていると。その二か月の間でこの十一月九日を迎えるわけですけれども、この一連の文書がその間にいろいろ挟まってきて、ただ、文科省の中でどういう決定がなされたのかというところが実は示されていないわけですね。そのところが明らかになってくれば、かなりこの問題もクリアになってくるんじゃないかと思いますので、この点はまた再度質問をしていきたいと思います。\r\n　それでは、著作権法改正案に対する質疑に入らせていただきます。\r\n　私からは、まず、障害者の情報アクセス機会の充実についてお伺いをしたいと思います。\r\n　今回の改正は主として、我が国が、いわゆる視覚障害者等による著作物の利用機会促進マラケシュ条約を締結するための国内法整備を行うものと承知しておりますけれども、視覚障害者のための著作物の複製等について定めた第三十七条第三項の改定事項、これは二点ありますけれども、この趣旨を改めて御説明をお願いいたします。",
          "speechURL": "https://kokkai.ndl.go.jp/txt/119615104X00920180517/116"
        },
        {
          "speechID": "119615104X00920180517_120",
          "speechOrder": 120,
          "speaker": "木戸口英司",
          "speech": "○木戸口英司君　今回の法については分かりましたけれども、やはり障害者、特に視聴覚障害というところを考えれば、こういう字幕放送等、非常に重要な支援につながることだと思います。\r\n　この点、大臣にお伺いいたしますけれども、今後、こういったこと、視聴覚障害ですね、字幕放送等、こういう放送での支援を高めていくための支援策、この著作権法との絡みの中でどのようなお考えがあるか、お聞きをしたいと思います。",
          "speechURL": "https://kokkai.ndl.go.jp/txt/119615104X00920180517/120"
        },
        {
          "speechID": "119615104X00920180517_122",
          "speechOrder": 122,
          "speaker": "木戸口英司",
          "speech": "○木戸口英司君　ありがとうございます。是非御検討をお願いしたいと思います。\r\n　そこで、公益社団法人全国学校図書館協議会等、図書館五団体があります。そこが出している図書館の障害者サービスにおける著作権法第三十七条第三項に基づく著作物の複製等に関するガイドラインでの対象者、これは結構広く対象者を示しております。視覚著作物をそのままの方式では利用することが困難な者とされ、視覚障害者や読字障害者に加え、肢体不自由者等も含める形で具体的に列挙されている。これは非常にすばらしいことだと思います。\r\n　ただ一方、指摘があるとおり、学校図書館、大学図書館、公共図書館、いずれにおいても障害者差別解消法の求める合理的配慮への取組はまだ低調であり、障害者サービスの実施率も上がってきているとはいえ、ハード面の整備にとどまっているということが指摘されております。\r\n　障害者の読書環境向上には、障害者が利用しやすい形式の図書の充実等、ソフト面の支援も重要ですし、読書バリアフリーに向けて各図書館の現状と課題をお伺いしたいと思います。また、あわせて、国立国会図書館、サピエ図書館を始めとする各図書館間の連携強化、先ほどもありましたけれども、改めてこの点について御所見をお伺いいたします。",
          "speechURL": "https://kokkai.ndl.go.jp/txt/119615104X00920180517/122"
        }
      ]
    }
  ]
}