{
  "member_name": "津島 淳",
  "kana": "つしま じゅん",
  "generated_at": "2025-11-09T11:50:39.320411+00:00",
  "keywords": [
    "障害福祉",
    "障害 福祉",
    "障がい 福祉",
    "障害者 福祉",
    "障がい者 福祉",
    "障害者",
    "障がい者",
    "障害児 福祉",
    "障がい児 福祉",
    "障害児",
    "障がい児",
    "医療的ケア児",
    "放課後等デイサービス",
    "特別児童扶養手当",
    "障害児福祉手当",
    "特別障害者手当"
  ],
  "meetings": [
    {
      "issueID": "121704319X00220250314",
      "date": "2025-03-14",
      "nameOfMeeting": "国土交通委員会",
      "issue": "第2号",
      "session": 217,
      "speeches": [
        {
          "speechID": "121704319X00220250314_245",
          "speechOrder": 245,
          "speaker": "津島淳",
          "speech": "○津島委員　自由民主党の津島淳であります。\r\n　本起草案の趣旨及び内容につきまして、提出者を代表して御説明申し上げます。\r\n　半島地域は、三方を海に囲まれ、幹線交通体系から遠く離れ、平地に恵まれず、水資源が乏しいなど国土資源の利用の面における制約から、産業基盤、交通基盤等の整備の面で他の地域に比較して低位にあります。こうしたことから、半島地域の振興を図るため、昭和六十年六月、半島振興法が衆議院建設委員長提案により時限立法として制定され、四度の改正を経て、現在四十年が経過しようとしております。\r\n　この間、本法に基づき二十三の地域が半島振興対策実施地域に指定され、半島振興計画に基づく各種の施策が講じられてきたことにより、道路等の基盤整備が進展するなど、一定の成果を上げてまいりました。\r\n　その一方で、半島地域は、全国平均を上回るペースで人口減少及び高齢化が進行しており、産業基盤及び生活環境の整備等における格差も依然として残っております。\r\n　また、令和六年能登半島地震では、地震の揺れや津波による被害に加え、代替ルートが少ない山がちな半島の先という特性から甚大な被害が発生し、半島防災の重要性を痛感させる惨禍となりました。\r\n　半島地域は、我が国及び国民の利益の保護及び増進に多様かつ重要な役割を担っており、その役割が十分に発揮されるよう、地理的及び自然的特性を生かした魅力の増進を図っていく必要があります。\r\n　本起草案は、このような最近における半島地域の社会経済情勢に鑑み、引き続き半島地域の振興を図り、半島防災の推進及び地方創生に資するため、所要の改正を行おうとするもので、その主な内容は次のとおりであります。\r\n　第一に、目的規定において、半島地域が担っている重要な役割として自然環境及び良好な景観の保全並びに多様な再生可能エネルギーの導入及び活用を追加すること、また、地域における創意工夫を生かすこと並びに半島振興のための連携及び協力の対象として半島地域と継続的な関係を有する半島地域外の人材を含むことを明記し、半島振興法の目的として半島防災及び地方創生を追加することとしております。\r\n　第二に、基本理念として、半島振興が、地方創生、地域の特性を生かした魅力の増進及び半島防災の三つの観点を踏まえて行われなければならないこととし、国及び都道府県の責務として、基本理念にのっとり施策を講ずべき旨を明らかにしております。\r\n　第三に、新たに国が半島振興基本方針を定めることとするとともに、都道府県の半島振興計画についても作成の努力義務化及び記載事項の充実を図ることとしております。\r\n　第四に、半島振興対策実施地域に係る国及び地方公共団体の配慮規定を拡充し、交通の確保、デジタル社会の形成に資する情報の流通の円滑化、医療の確保、障害福祉サービス等の確保、児童の福祉の増進、教育の充実、自然環境の保全及び再生、再生可能エネルギーの利用の推進、移住等の促進、半島防災の推進及び実効性の確保、感染症が発生した場合における生活に必要な物資の確保、小規模な集落への配慮等について規定することとしております。\r\n　第五に、半島振興に係る体制の整備を図るため、地方公共団体等の半島振興に携わる関係者が協議会を組織することができることとするほか、半島振興基本方針及び半島振興計画に係る主務大臣として内閣総理大臣を追加することとしております。\r\n　第六に、法律の有効期限を令和十七年三月三十一日まで十年間延長することとしております。\r\n　以上が、本起草案の趣旨及び主な内容であります。\r\n　何とぞ速やかに御賛同いただきますようお願い申し上げます。\r\n　　　　―――――――――――――\r\n　半島振興法の一部を改正する法律案\r\n　　　　〔本号末尾に掲載〕\r\n　　　　―――――――――――――",
          "speechURL": "https://kokkai.ndl.go.jp/txt/121704319X00220250314/245"
        }
      ]
    },
    {
      "issueID": "121104319X00220230310",
      "date": "2023-03-10",
      "nameOfMeeting": "国土交通委員会",
      "issue": "第2号",
      "session": 211,
      "speeches": [
        {
          "speechID": "121104319X00220230310_014",
          "speechOrder": 14,
          "speaker": "津島淳",
          "speech": "○津島委員　ありがとうございます。\r\n　大臣所信の中にもありましたけれども、今年は関東大震災の発災から百年、そして、あしたが東日本大震災発災から十二年ということであります。改めて、お亡くなりになられた方の御冥福をお祈り申し上げますとともに、被災された方々にお見舞い、まだ見つかっていない方もいらっしゃる、こういうことがあります、お見舞いを申し上げたいと思います。\r\n　被災三県のみならず、列島、やはりあらゆる災害リスクというのに直面をしている、これが現実であります。地震、津波についての新想定ということも示されたということもありますので、やはり国土強靱化の取組をしっかりと進めていただく中で、それを実際に支える人材というもの、今ほど除排雪のマンパワーの、人材の話がございましたけれども、そういったことも含めて、人材確保ということもしっかり取り組んでいかなければいけない課題だろう、そういうように考えております。是非よろしくお願いします。\r\n　時間の関係で、もしかしたらこれが最後の質問になるかもしれません。バリアフリーの推進についてお尋ねをします。\r\n　視覚障害者の方がホームから転落をされて命を落とすという痛ましい事件がやはりまだ続いているんですね。コロナの行動制限が緩和されたことで、やはりいろいろな人が外に出るようになったということで、段差解消というニーズというのが再び顕在化していると思います。\r\n　そこで、やはりホームドアの設置であるとかエレベーターの設置、そしてノンステップバスの導入支援ということをしっかりやっていく必要があります。これは、先ほど来も子育て支援ということを私は言っていますけれども、これは当然、子育て支援に、子供連れの方にもプラスになるのは明らかであります。\r\n　一方で、こうしたバリアフリーに関する設備を整えても、利用する障害者の方だとか、子供連れの方、ベビーカーの方に心ない言動がなされる、そういう事例も散見をされます。車椅子でエレベーターを利用しようと思っていたら、どんどん健常者の方に抜かれてしまった、乗れない、そんな話があるわけですね。つまりは、誰のための設備なのかということに思いを致し、やはり一歩引く、譲る、そういう心のバリアフリーということも重要なんだと思います。\r\n　そういったハードとソフト一体となった取組、このバリアフリー推進について、いかがでしょうか。政府参考人にお尋ねします。",
          "speechURL": "https://kokkai.ndl.go.jp/txt/121104319X00220230310/14"
        }
      ]
    }
  ]
}